[{"skill_judge":0,"cd":5,"par1":0,"par2":0,"par3":0,"par4":0,"view_target":0,"client_type":1,"target":20,"consume_value":0,"scope":1,"function_id":111,"consume_type":0,"id":111,"buff":0},{"skill_judge":0,"cd":3,"par1":0,"par2":0,"par3":0,"par4":0,"view_target":3,"client_type":1,"target":7,"consume_value":0,"scope":1,"function_id":112,"consume_type":0,"id":112,"buff":0},{"skill_judge":0,"cd":3,"par1":0,"par2":0,"par3":0,"par4":0,"view_target":0,"client_type":1,"target":4,"consume_value":0,"scope":0,"function_id":113,"consume_type":0,"id":113,"buff":0},{"skill_judge":0,"cd":5,"par1":2,"par2":2,"par3":3,"par4":121,"view_target":0,"client_type":1,"target":1,"consume_value":0,"scope":4,"function_id":121,"consume_type":0,"id":121,"buff":0},{"skill_judge":0,"cd":5,"par1":0,"par2":0,"par3":0,"par4":0,"view_target":0,"client_type":1,"target":3,"consume_value":0,"scope":0,"function_id":122,"consume_type":0,"id":122,"buff":1},{"skill_judge":0,"cd":7,"par1":3,"par2":0,"par3":0,"par4":0,"view_target":0,"client_type":1,"target":2,"consume_value":0,"scope":0,"function_id":123,"consume_type":0,"id":123,"buff":0},{"skill_judge":0,"cd":6,"par1":0,"par2":0,"par3":0,"par4":0,"view_target":0,"client_type":1,"target":3,"consume_value":0,"scope":0,"function_id":211,"consume_type":0,"id":211,"buff":4},{"skill_judge":0,"cd":5,"par1":0,"par2":0,"par3":0,"par4":0,"view_target":0,"client_type":1,"target":8,"consume_value":0,"scope":1,"function_id":212,"consume_type":0,"id":212,"buff":5},{"skill_judge":0,"cd":4,"par1":5,"par2":2,"par3":0,"par4":0,"view_target":0,"client_type":1,"target":17,"consume_value":0,"scope":0,"function_id":213,"consume_type":0,"id":213,"buff":0},{"skill_judge":0,"cd":4,"par1":0,"par2":0,"par3":0,"par4":0,"view_target":0,"client_type":1,"target":10,"consume_value":0,"scope":1,"function_id":221,"consume_type":0,"id":221,"buff":6},{"skill_judge":0,"cd":3,"par1":0,"par2":0,"par3":0,"par4":0,"view_target":0,"client_type":1,"target":6,"consume_value":0,"scope":0,"function_id":222,"consume_type":0,"id":222,"buff":0},{"skill_judge":0,"cd":6,"par1":0,"par2":0,"par3":0,"par4":0,"view_target":0,"client_type":1,"target":18,"consume_value":0,"scope":1,"function_id":223,"consume_type":0,"id":223,"buff":0},{"skill_judge":1,"cd":4,"par1":2,"par2":0,"par3":0,"par4":0,"view_target":0,"client_type":1,"target":3,"consume_value":0,"scope":0,"function_id":311,"consume_type":0,"id":311,"buff":2},{"skill_judge":0,"cd":1,"par1":0,"par2":0,"par3":0,"par4":0,"view_target":3,"client_type":1,"target":9,"consume_value":0,"scope":1,"function_id":312,"consume_type":0,"id":312,"buff":10},{"skill_judge":0,"cd":5,"par1":3,"par2":2,"par3":0,"par4":0,"view_target":0,"client_type":1,"target":14,"consume_value":0,"scope":3,"function_id":313,"consume_type":0,"id":313,"buff":0},{"skill_judge":0,"cd":6,"par1":2,"par2":0,"par3":0,"par4":0,"view_target":0,"client_type":1,"target":12,"consume_value":0,"scope":2,"function_id":321,"consume_type":0,"id":321,"buff":0},{"skill_judge":0,"cd":5,"par1":0,"par2":0,"par3":0,"par4":0,"view_target":0,"client_type":1,"target":3,"consume_value":0,"scope":0,"function_id":322,"consume_type":0,"id":322,"buff":3},{"skill_judge":0,"cd":0,"par1":7,"par2":322,"par3":0,"par4":0,"view_target":0,"client_type":1,"target":2,"consume_value":0,"scope":0,"function_id":323,"consume_type":0,"id":323,"buff":0},{"skill_judge":0,"cd":3,"par1":0,"par2":0,"par3":0,"par4":0,"view_target":3,"client_type":1,"target":9,"consume_value":0,"scope":1,"function_id":324,"consume_type":0,"id":324,"buff":12},{"skill_judge":4,"cd":0,"par1":2,"par2":0,"par3":0,"par4":0,"view_target":0,"client_type":1,"target":2,"consume_value":0,"scope":0,"function_id":331,"consume_type":0,"id":331,"buff":0},{"skill_judge":0,"cd":0,"par1":3,"par2":0,"par3":0,"par4":0,"view_target":0,"client_type":2,"target":1,"consume_value":6,"scope":4,"function_id":411,"consume_type":1,"id":411,"buff":0},{"skill_judge":0,"cd":0,"par1":2,"par2":0,"par3":0,"par4":0,"view_target":0,"client_type":2,"target":1,"consume_value":5,"scope":5,"function_id":412,"consume_type":1,"id":412,"buff":0},{"skill_judge":0,"cd":0,"par1":0,"par2":0,"par3":0,"par4":0,"view_target":3,"client_type":2,"target":7,"consume_value":3,"scope":1,"function_id":421,"consume_type":1,"id":421,"buff":0},{"skill_judge":0,"cd":0,"par1":0,"par2":0,"par3":0,"par4":0,"view_target":0,"client_type":2,"target":16,"consume_value":4,"scope":1,"function_id":422,"consume_type":1,"id":422,"buff":0},{"skill_judge":3,"cd":0,"par1":4,"par2":2,"par3":0,"par4":0,"view_target":0,"client_type":2,"target":7,"consume_value":0,"scope":1,"function_id":423,"consume_type":1,"id":423,"buff":0},{"skill_judge":2,"cd":0,"par1":2,"par2":11004,"par3":0,"par4":0,"view_target":0,"client_type":2,"target":19,"consume_value":12,"scope":2,"function_id":431,"consume_type":1,"id":431,"buff":14},{"skill_judge":2,"cd":0,"par1":3,"par2":6,"par3":0,"par4":0,"view_target":0,"client_type":2,"target":1,"consume_value":0,"scope":3,"function_id":432,"consume_type":1,"id":432,"buff":0},{"skill_judge":2,"cd":0,"par1":3,"par2":0,"par3":0,"par4":0,"view_target":0,"client_type":2,"target":2,"consume_value":0,"scope":1,"function_id":433,"consume_type":1,"id":433,"buff":0},{"skill_judge":0,"cd":5,"par1":2,"par2":4,"par3":0,"par4":0,"view_target":0,"client_type":1,"target":2,"consume_value":0,"scope":0,"function_id":999,"consume_type":0,"id":999,"buff":0},{"skill_judge":0,"cd":5,"par1":7,"par2":0,"par3":0,"par4":0,"view_target":0,"client_type":1,"target":6,"consume_value":0,"scope":0,"function_id":11001,"consume_type":0,"id":11001,"buff":0},{"skill_judge":0,"cd":7,"par1":22001,"par2":1,"par3":0,"par4":0,"view_target":0,"client_type":1,"target":9,"consume_value":0,"scope":1,"function_id":11002,"consume_type":0,"id":11002,"buff":0},{"skill_judge":0,"cd":6,"par1":5,"par2":0,"par3":0,"par4":0,"view_target":0,"client_type":1,"target":23,"consume_value":0,"scope":0,"function_id":11004,"consume_type":0,"id":11004,"buff":20},{"skill_judge":0,"cd":5,"par1":5,"par2":0,"par3":0,"par4":0,"view_target":0,"client_type":1,"target":23,"consume_value":0,"scope":0,"function_id":11005,"consume_type":0,"id":11005,"buff":0},{"skill_judge":0,"cd":5,"par1":5,"par2":0,"par3":0,"par4":0,"view_target":0,"client_type":1,"target":27,"consume_value":0,"scope":5,"function_id":11007,"consume_type":0,"id":11007,"buff":0},{"skill_judge":0,"cd":5,"par1":5,"par2":0,"par3":0,"par4":0,"view_target":0,"client_type":1,"target":27,"consume_value":0,"scope":3,"function_id":11008,"consume_type":0,"id":11008,"buff":0},{"skill_judge":0,"cd":5,"par1":5,"par2":0,"par3":0,"par4":0,"view_target":0,"client_type":1,"target":21,"consume_value":0,"scope":6,"function_id":11009,"consume_type":0,"id":11009,"buff":0},{"skill_judge":0,"cd":3,"par1":0,"par2":0,"par3":0,"par4":0,"view_target":0,"client_type":1,"target":27,"consume_value":0,"scope":2,"function_id":13001,"consume_type":0,"id":13001,"buff":0},{"skill_judge":0,"cd":10,"par1":10,"par2":0,"par3":0,"par4":0,"view_target":0,"client_type":1,"target":23,"consume_value":0,"scope":0,"function_id":13002,"consume_type":0,"id":13002,"buff":0},{"skill_judge":0,"cd":5,"par1":22003,"par2":3,"par3":0,"par4":0,"view_target":0,"client_type":1,"target":9,"consume_value":0,"scope":1,"function_id":13003,"consume_type":0,"id":13003,"buff":0},{"skill_judge":0,"cd":3,"par1":0,"par2":0,"par3":0,"par4":0,"view_target":0,"client_type":1,"target":23,"consume_value":0,"scope":0,"function_id":13004,"consume_type":0,"id":13004,"buff":0},{"skill_judge":0,"cd":10,"par1":4,"par2":0,"par3":0,"par4":0,"view_target":0,"client_type":1,"target":21,"consume_value":0,"scope":6,"function_id":13005,"consume_type":0,"id":13005,"buff":0},{"skill_judge":0,"cd":0,"par1":0,"par2":0,"par3":0,"par4":0,"view_target":3,"client_type":0,"target":1,"consume_value":0,"scope":0,"function_id":20001,"consume_type":0,"id":20001,"buff":0},{"skill_judge":0,"cd":0,"par1":0,"par2":0,"par3":0,"par4":0,"view_target":0,"client_type":0,"target":3,"consume_value":0,"scope":0,"function_id":20002,"consume_type":0,"id":20002,"buff":8},{"skill_judge":0,"cd":0,"par1":2,"par2":0,"par3":0,"par4":0,"view_target":0,"client_type":0,"target":2,"consume_value":0,"scope":0,"function_id":20003,"consume_type":0,"id":20003,"buff":0},{"skill_judge":0,"cd":0,"par1":3,"par2":0,"par3":0,"par4":0,"view_target":0,"client_type":0,"target":2,"consume_value":0,"scope":0,"function_id":20004,"consume_type":0,"id":20004,"buff":0},{"skill_judge":0,"cd":0,"par1":2,"par2":0,"par3":0,"par4":0,"view_target":0,"client_type":0,"target":2,"consume_value":0,"scope":0,"function_id":20005,"consume_type":0,"id":20005,"buff":0}]