{"config":{"output_file":null,"full_docs":false,"pub_only":true,"reachable_only":true,"distro_crate":false,"signatures":false,"borrow_data":false},"version":"0.19.0","compilation":{"directory":"C:\\Users\\Administrator\\.cargo\\registry\\src\\github.com-1ecc6299db9ec823\\tokio-executor-0.1.8","program":"C:\\Users\\Administrator\\.rustup\\toolchains\\stable-x86_64-pc-windows-gnu\\bin\\rls.exe","arguments":["--crate-name","tokio_executor","C:\\Users\\Administrator\\.cargo\\registry\\src\\github.com-1ecc6299db9ec823\\tokio-executor-0.1.8\\src\\lib.rs","--color","never","--crate-type","lib","--emit=dep-info,metadata","-C","debuginfo=2","-C","metadata=59b5d4b5d779eace","-C","extra-filename=-59b5d4b5d779eace","--out-dir","f:\\rust\\MyRust\\gateserver\\target\\rls\\debug\\deps","-L","dependency=f:\\rust\\MyRust\\gateserver\\target\\rls\\debug\\deps","--extern","crossbeam_utils=f:\\rust\\MyRust\\gateserver\\target\\rls\\debug\\deps\\libcrossbeam_utils-4f4c6084aab24e5b.rmeta","--extern","futures=f:\\rust\\MyRust\\gateserver\\target\\rls\\debug\\deps\\libfutures-515f9cc980c58ef6.rmeta","--cap-lints","allow","--error-format=json","--sysroot","C:\\Users\\Administrator\\.rustup/toolchains/stable-x86_64-pc-windows-gnu"],"output":"f:\\rust\\MyRust\\gateserver\\target\\rls\\debug\\deps\\libtokio_executor-59b5d4b5d779eace.rmeta"},"prelude":{"crate_id":{"name":"tokio_executor","disambiguator":[1028986606080240613,15959824433165326835]},"crate_root":"C:\\Users\\Administrator\\.cargo\\registry\\src\\github.com-1ecc6299db9ec823\\tokio-executor-0.1.8\\src","external_crates":[{"file_name":"C:\\Users\\Administrator\\.cargo\\registry\\src\\github.com-1ecc6299db9ec823\\tokio-executor-0.1.8\\src\\lib.rs","num":1,"id":{"name":"std","disambiguator":[17754226726312282658,4076905949603487160]}},{"file_name":"C:\\Users\\Administrator\\.cargo\\registry\\src\\github.com-1ecc6299db9ec823\\tokio-executor-0.1.8\\src\\lib.rs","num":2,"id":{"name":"core","disambiguator":[14440509561659192608,317633866642573698]}},{"file_name":"C:\\Users\\Administrator\\.cargo\\registry\\src\\github.com-1ecc6299db9ec823\\tokio-executor-0.1.8\\src\\lib.rs","num":3,"id":{"name":"compiler_builtins","disambiguator":[16214886559712252845,1623273168981509368]}},{"file_name":"C:\\Users\\Administrator\\.cargo\\registry\\src\\github.com-1ecc6299db9ec823\\tokio-executor-0.1.8\\src\\lib.rs","num":4,"id":{"name":"rustc_std_workspace_core","disambiguator":[3509281774579603838,13144099113451520591]}},{"file_name":"C:\\Users\\Administrator\\.cargo\\registry\\src\\github.com-1ecc6299db9ec823\\tokio-executor-0.1.8\\src\\lib.rs","num":5,"id":{"name":"alloc","disambiguator":[11501227129415035301,2278099145643430660]}},{"file_name":"C:\\Users\\Administrator\\.cargo\\registry\\src\\github.com-1ecc6299db9ec823\\tokio-executor-0.1.8\\src\\lib.rs","num":6,"id":{"name":"libc","disambiguator":[4852698717079168062,8821218321849336759]}},{"file_name":"C:\\Users\\Administrator\\.cargo\\registry\\src\\github.com-1ecc6299db9ec823\\tokio-executor-0.1.8\\src\\lib.rs","num":7,"id":{"name":"unwind","disambiguator":[2970414798178766284,12464411377570547827]}},{"file_name":"C:\\Users\\Administrator\\.cargo\\registry\\src\\github.com-1ecc6299db9ec823\\tokio-executor-0.1.8\\src\\lib.rs","num":8,"id":{"name":"cfg_if","disambiguator":[18043833326731472338,16860295939395283854]}},{"file_name":"C:\\Users\\Administrator\\.cargo\\registry\\src\\github.com-1ecc6299db9ec823\\tokio-executor-0.1.8\\src\\lib.rs","num":9,"id":{"name":"backtrace","disambiguator":[3938440098624159483,15371459087357312146]}},{"file_name":"C:\\Users\\Administrator\\.cargo\\registry\\src\\github.com-1ecc6299db9ec823\\tokio-executor-0.1.8\\src\\lib.rs","num":10,"id":{"name":"rustc_demangle","disambiguator":[10824472699003730294,5430748819956168801]}},{"file_name":"C:\\Users\\Administrator\\.cargo\\registry\\src\\github.com-1ecc6299db9ec823\\tokio-executor-0.1.8\\src\\lib.rs","num":11,"id":{"name":"backtrace_sys","disambiguator":[15385697880778141559,4635661529098517216]}},{"file_name":"C:\\Users\\Administrator\\.cargo\\registry\\src\\github.com-1ecc6299db9ec823\\tokio-executor-0.1.8\\src\\lib.rs","num":12,"id":{"name":"hashbrown","disambiguator":[7251163173618888154,296046126038531172]}},{"file_name":"C:\\Users\\Administrator\\.cargo\\registry\\src\\github.com-1ecc6299db9ec823\\tokio-executor-0.1.8\\src\\lib.rs","num":13,"id":{"name":"rustc_std_workspace_alloc","disambiguator":[3425786209665352775,2104592579185322956]}},{"file_name":"C:\\Users\\Administrator\\.cargo\\registry\\src\\github.com-1ecc6299db9ec823\\tokio-executor-0.1.8\\src\\lib.rs","num":14,"id":{"name":"panic_unwind","disambiguator":[4242707251431438356,10403915645989066416]}},{"file_name":"C:\\Users\\Administrator\\.cargo\\registry\\src\\github.com-1ecc6299db9ec823\\tokio-executor-0.1.8\\src\\lib.rs","num":15,"id":{"name":"crossbeam_utils","disambiguator":[12946054221125327669,7957229709682428824]}},{"file_name":"C:\\Users\\Administrator\\.cargo\\registry\\src\\github.com-1ecc6299db9ec823\\tokio-executor-0.1.8\\src\\lib.rs","num":16,"id":{"name":"cfg_if","disambiguator":[16667018505396256223,5625436889170652735]}},{"file_name":"C:\\Users\\Administrator\\.cargo\\registry\\src\\github.com-1ecc6299db9ec823\\tokio-executor-0.1.8\\src\\lib.rs","num":17,"id":{"name":"lazy_static","disambiguator":[138886175326615119,13093497193639800696]}},{"file_name":"C:\\Users\\Administrator\\.cargo\\registry\\src\\github.com-1ecc6299db9ec823\\tokio-executor-0.1.8\\src\\lib.rs","num":18,"id":{"name":"futures","disambiguator":[2197765917231091748,6425706503530463562]}}],"span":{"file_name":"C:\\Users\\Administrator\\.cargo\\registry\\src\\github.com-1ecc6299db9ec823\\tokio-executor-0.1.8\\src\\lib.rs","byte_start":0,"byte_end":2865,"line_start":1,"line_end":70,"column_start":1,"column_end":30}},"imports":[{"kind":"Use","ref_id":{"krate":0,"index":33},"span":{"file_name":"C:\\Users\\Administrator\\.cargo\\registry\\src\\github.com-1ecc6299db9ec823\\tokio-executor-0.1.8\\src\\lib.rs","byte_start":2692,"byte_end":2697,"line_start":66,"line_end":66,"column_start":17,"column_end":22},"alias_span":null,"name":"enter","value":"","parent":{"krate":0,"index":0}},{"kind":"Use","ref_id":{"krate":0,"index":35},"span":{"file_name":"C:\\Users\\Administrator\\.cargo\\registry\\src\\github.com-1ecc6299db9ec823\\tokio-executor-0.1.8\\src\\lib.rs","byte_start":2699,"byte_end":2703,"line_start":66,"line_end":66,"column_start":24,"column_end":28},"alias_span":null,"name":"exit","value":"","parent":{"krate":0,"index":0}},{"kind":"Use","ref_id":{"krate":0,"index":22},"span":{"file_name":"C:\\Users\\Administrator\\.cargo\\registry\\src\\github.com-1ecc6299db9ec823\\tokio-executor-0.1.8\\src\\lib.rs","byte_start":2705,"byte_end":2710,"line_start":66,"line_end":66,"column_start":30,"column_end":35},"alias_span":null,"name":"Enter","value":"","parent":{"krate":0,"index":0}},{"kind":"Use","ref_id":{"krate":0,"index":25},"span":{"file_name":"C:\\Users\\Administrator\\.cargo\\registry\\src\\github.com-1ecc6299db9ec823\\tokio-executor-0.1.8\\src\\lib.rs","byte_start":2712,"byte_end":2722,"line_start":66,"line_end":66,"column_start":37,"column_end":47},"alias_span":null,"name":"EnterError","value":"","parent":{"krate":0,"index":0}},{"kind":"Use","ref_id":{"krate":0,"index":194},"span":{"file_name":"C:\\Users\\Administrator\\.cargo\\registry\\src\\github.com-1ecc6299db9ec823\\tokio-executor-0.1.8\\src\\lib.rs","byte_start":2740,"byte_end":2750,"line_start":67,"line_end":67,"column_start":16,"column_end":26},"alias_span":null,"name":"SpawnError","value":"","parent":{"krate":0,"index":0}},{"kind":"Use","ref_id":{"krate":0,"index":76},"span":{"file_name":"C:\\Users\\Administrator\\.cargo\\registry\\src\\github.com-1ecc6299db9ec823\\tokio-executor-0.1.8\\src\\lib.rs","byte_start":2770,"byte_end":2778,"line_start":68,"line_end":68,"column_start":19,"column_end":27},"alias_span":null,"name":"Executor","value":"","parent":{"krate":0,"index":0}},{"kind":"Use","ref_id":{"krate":0,"index":113},"span":{"file_name":"C:\\Users\\Administrator\\.cargo\\registry\\src\\github.com-1ecc6299db9ec823\\tokio-executor-0.1.8\\src\\lib.rs","byte_start":2797,"byte_end":2802,"line_start":69,"line_end":69,"column_start":18,"column_end":23},"alias_span":null,"name":"spawn","value":"","parent":{"krate":0,"index":0}},{"kind":"Use","ref_id":{"krate":0,"index":115},"span":{"file_name":"C:\\Users\\Administrator\\.cargo\\registry\\src\\github.com-1ecc6299db9ec823\\tokio-executor-0.1.8\\src\\lib.rs","byte_start":2804,"byte_end":2816,"line_start":69,"line_end":69,"column_start":25,"column_end":37},"alias_span":null,"name":"with_default","value":"","parent":{"krate":0,"index":0}},{"kind":"Use","ref_id":{"krate":0,"index":198},"span":{"file_name":"C:\\Users\\Administrator\\.cargo\\registry\\src\\github.com-1ecc6299db9ec823\\tokio-executor-0.1.8\\src\\lib.rs","byte_start":2818,"byte_end":2833,"line_start":69,"line_end":69,"column_start":39,"column_end":54},"alias_span":null,"name":"DefaultExecutor","value":"","parent":{"krate":0,"index":0}},{"kind":"Use","ref_id":{"krate":0,"index":169},"span":{"file_name":"C:\\Users\\Administrator\\.cargo\\registry\\src\\github.com-1ecc6299db9ec823\\tokio-executor-0.1.8\\src\\lib.rs","byte_start":2851,"byte_end":2864,"line_start":70,"line_end":70,"column_start":16,"column_end":29},"alias_span":null,"name":"TypedExecutor","value":"","parent":{"krate":0,"index":0}}],"defs":[{"kind":"Mod","id":{"krate":0,"index":0},"span":{"file_name":"C:\\Users\\Administrator\\.cargo\\registry\\src\\github.com-1ecc6299db9ec823\\tokio-executor-0.1.8\\src\\lib.rs","byte_start":0,"byte_end":2865,"line_start":1,"line_end":70,"column_start":1,"column_end":30},"name":"","qualname":"::","value":"C:\\Users\\Administrator\\.cargo\\registry\\src\\github.com-1ecc6299db9ec823\\tokio-executor-0.1.8\\src\\lib.rs","parent":null,"children":[{"krate":0,"index":10},{"krate":0,"index":11},{"krate":0,"index":12},{"krate":0,"index":13},{"krate":0,"index":14},{"krate":0,"index":61},{"krate":0,"index":73},{"krate":0,"index":83},{"krate":0,"index":130},{"krate":0,"index":167},{"krate":0,"index":178},{"krate":0,"index":183},{"krate":0,"index":184},{"krate":0,"index":185},{"krate":0,"index":189}],"decl_id":null,"docs":" Task execution related traits and utilities.","sig":null,"attributes":[{"value":"deny(missing_docs, missing_debug_implementations, warnings)","span":{"file_name":"C:\\Users\\Administrator\\.cargo\\registry\\src\\github.com-1ecc6299db9ec823\\tokio-executor-0.1.8\\src\\lib.rs","byte_start":0,"byte_end":63,"line_start":1,"line_end":1,"column_start":1,"column_end":64}},{"value":"allow(rust_2018_idioms)","span":{"file_name":"C:\\Users\\Administrator\\.cargo\\registry\\src\\github.com-1ecc6299db9ec823\\tokio-executor-0.1.8\\src\\lib.rs","byte_start":183,"byte_end":210,"line_start":4,"line_end":4,"column_start":1,"column_end":28}}]},{"kind":"Struct","id":{"krate":0,"index":22},"span":{"file_name":"C:\\Users\\Administrator\\.cargo\\registry\\src\\github.com-1ecc6299db9ec823\\tokio-executor-0.1.8\\src\\enter.rs","byte_start":3160,"byte_end":3165,"line_start":13,"line_end":13,"column_start":12,"column_end":17},"name":"Enter","qualname":"::enter::Enter","value":"Enter {  }","parent":null,"children":[{"krate":0,"index":23},{"krate":0,"index":24}],"decl_id":null,"docs":" Represents an executor context.","sig":null,"attributes":[]},{"kind":"Struct","id":{"krate":0,"index":25},"span":{"file_name":"C:\\Users\\Administrator\\.cargo\\registry\\src\\github.com-1ecc6299db9ec823\\tokio-executor-0.1.8\\src\\enter.rs","byte_start":3321,"byte_end":3331,"line_start":20,"line_end":20,"column_start":12,"column_end":22},"name":"EnterError","qualname":"::enter::EnterError","value":"EnterError {  }","parent":null,"children":[{"krate":0,"index":26}],"decl_id":null,"docs":" An error returned by `enter` if an execution scope has already been\n entered.\n","sig":null,"attributes":[]},{"kind":"Function","id":{"krate":0,"index":33},"span":{"file_name":"C:\\Users\\Administrator\\.cargo\\registry\\src\\github.com-1ecc6299db9ec823\\tokio-executor-0.1.8\\src\\enter.rs","byte_start":4342,"byte_end":4347,"line_start":55,"line_end":55,"column_start":8,"column_end":13},"name":"enter","qualname":"::enter::enter","value":"fn () -> Result<Enter, EnterError>","parent":null,"children":[],"decl_id":null,"docs":" Marks the current thread as being within the dynamic extent of an\n executor.","sig":null,"attributes":[]},{"kind":"Function","id":{"krate":0,"index":35},"span":{"file_name":"C:\\Users\\Administrator\\.cargo\\registry\\src\\github.com-1ecc6299db9ec823\\tokio-executor-0.1.8\\src\\enter.rs","byte_start":4899,"byte_end":4903,"line_start":78,"line_end":78,"column_start":8,"column_end":12},"name":"exit","qualname":"::enter::exit","value":"fn <F, R> (f: F) -> R","parent":null,"children":[],"decl_id":null,"docs":"","sig":null,"attributes":[]},{"kind":"Method","id":{"krate":0,"index":46},"span":{"file_name":"C:\\Users\\Administrator\\.cargo\\registry\\src\\github.com-1ecc6299db9ec823\\tokio-executor-0.1.8\\src\\enter.rs","byte_start":5560,"byte_end":5567,"line_start":109,"line_end":109,"column_start":12,"column_end":19},"name":"on_exit","qualname":"<Enter>::on_exit","value":"fn <F> (&mut self, f: F) -> ()","parent":null,"children":[],"decl_id":null,"docs":" Register a callback to be invoked if and when the thread\n ceased to act as an executor.\n","sig":null,"attributes":[]},{"kind":"Method","id":{"krate":0,"index":48},"span":{"file_name":"C:\\Users\\Administrator\\.cargo\\registry\\src\\github.com-1ecc6299db9ec823\\tokio-executor-0.1.8\\src\\enter.rs","byte_start":5921,"byte_end":5935,"line_start":121,"line_end":121,"column_start":12,"column_end":26},"name":"make_permanent","qualname":"<Enter>::make_permanent","value":"fn (mut self) -> ()","parent":null,"children":[],"decl_id":null,"docs":" Treat the remainder of execution on this thread as part of an\n executor; used mostly for thread pool worker threads.","sig":null,"attributes":[]},{"kind":"Method","id":{"krate":0,"index":49},"span":{"file_name":"C:\\Users\\Administrator\\.cargo\\registry\\src\\github.com-1ecc6299db9ec823\\tokio-executor-0.1.8\\src\\enter.rs","byte_start":6110,"byte_end":6118,"line_start":127,"line_end":127,"column_start":12,"column_end":20},"name":"block_on","qualname":"<Enter>::block_on","value":"fn <F> (&mut self, f: F) -> Result<F::Item, F::Error>","parent":null,"children":[],"decl_id":null,"docs":" Blocks the thread on the specified future, returning the value with\n which that future completes.\n","sig":null,"attributes":[]},{"kind":"Struct","id":{"krate":0,"index":194},"span":{"file_name":"C:\\Users\\Administrator\\.cargo\\registry\\src\\github.com-1ecc6299db9ec823\\tokio-executor-0.1.8\\src\\error.rs","byte_start":7384,"byte_end":7394,"line_start":14,"line_end":14,"column_start":12,"column_end":22},"name":"SpawnError","qualname":"::error::SpawnError","value":"SpawnError {  }","parent":null,"children":[{"krate":0,"index":195}],"decl_id":null,"docs":" Errors returned by `Executor::spawn`.","sig":null,"attributes":[]},{"kind":"Method","id":{"krate":0,"index":65},"span":{"file_name":"C:\\Users\\Administrator\\.cargo\\registry\\src\\github.com-1ecc6299db9ec823\\tokio-executor-0.1.8\\src\\error.rs","byte_start":7526,"byte_end":7534,"line_start":20,"line_end":20,"column_start":12,"column_end":20},"name":"shutdown","qualname":"<SpawnError>::shutdown","value":"fn () -> Self","parent":null,"children":[],"decl_id":null,"docs":" Return a new `SpawnError` reflecting a shutdown executor failure.\n","sig":null,"attributes":[]},{"kind":"Method","id":{"krate":0,"index":66},"span":{"file_name":"C:\\Users\\Administrator\\.cargo\\registry\\src\\github.com-1ecc6299db9ec823\\tokio-executor-0.1.8\\src\\error.rs","byte_start":7684,"byte_end":7695,"line_start":25,"line_end":25,"column_start":12,"column_end":23},"name":"at_capacity","qualname":"<SpawnError>::at_capacity","value":"fn () -> Self","parent":null,"children":[],"decl_id":null,"docs":" Return a new `SpawnError` reflecting an executor at capacity failure.\n","sig":null,"attributes":[]},{"kind":"Method","id":{"krate":0,"index":67},"span":{"file_name":"C:\\Users\\Administrator\\.cargo\\registry\\src\\github.com-1ecc6299db9ec823\\tokio-executor-0.1.8\\src\\error.rs","byte_start":7842,"byte_end":7853,"line_start":30,"line_end":30,"column_start":12,"column_end":23},"name":"is_shutdown","qualname":"<SpawnError>::is_shutdown","value":"fn (&self) -> bool","parent":null,"children":[],"decl_id":null,"docs":" Returns `true` if the error reflects a shutdown executor failure.\n","sig":null,"attributes":[]},{"kind":"Method","id":{"krate":0,"index":68},"span":{"file_name":"C:\\Users\\Administrator\\.cargo\\registry\\src\\github.com-1ecc6299db9ec823\\tokio-executor-0.1.8\\src\\error.rs","byte_start":7992,"byte_end":8006,"line_start":35,"line_end":35,"column_start":12,"column_end":26},"name":"is_at_capacity","qualname":"<SpawnError>::is_at_capacity","value":"fn (&self) -> bool","parent":null,"children":[],"decl_id":null,"docs":" Returns `true` if the error reflects an executor at capacity failure.\n","sig":null,"attributes":[]},{"kind":"Trait","id":{"krate":0,"index":76},"span":{"file_name":"C:\\Users\\Administrator\\.cargo\\registry\\src\\github.com-1ecc6299db9ec823\\tokio-executor-0.1.8\\src\\executor.rs","byte_start":11205,"byte_end":11213,"line_start":67,"line_end":67,"column_start":11,"column_end":19},"name":"Executor","qualname":"::executor::Executor","value":"Executor","parent":null,"children":[{"krate":0,"index":77},{"krate":0,"index":78}],"decl_id":null,"docs":" A value that executes futures.","sig":null,"attributes":[]},{"kind":"Method","id":{"krate":0,"index":77},"span":{"file_name":"C:\\Users\\Administrator\\.cargo\\registry\\src\\github.com-1ecc6299db9ec823\\tokio-executor-0.1.8\\src\\executor.rs","byte_start":12157,"byte_end":12162,"line_start":95,"line_end":95,"column_start":8,"column_end":13},"name":"spawn","qualname":"::executor::Executor::spawn","value":"fn (&mut self, future: Box<Future<Item = (), Error = ()> + Send>) -> Result<(), SpawnError>","parent":{"krate":0,"index":76},"children":[],"decl_id":null,"docs":" Spawns a future object to run on this executor.","sig":null,"attributes":[]},{"kind":"Method","id":{"krate":0,"index":78},"span":{"file_name":"C:\\Users\\Administrator\\.cargo\\registry\\src\\github.com-1ecc6299db9ec823\\tokio-executor-0.1.8\\src\\executor.rs","byte_start":13488,"byte_end":13494,"line_start":135,"line_end":135,"column_start":8,"column_end":14},"name":"status","qualname":"::executor::Executor::status","value":"fn (&self) -> Result<(), SpawnError>","parent":{"krate":0,"index":76},"children":[],"decl_id":null,"docs":" Provides a best effort **hint** to whether or not `spawn` will succeed.","sig":null,"attributes":[]},{"kind":"Struct","id":{"krate":0,"index":198},"span":{"file_name":"C:\\Users\\Administrator\\.cargo\\registry\\src\\github.com-1ecc6299db9ec823\\tokio-executor-0.1.8\\src\\global.rs","byte_start":14478,"byte_end":14493,"line_start":18,"line_end":18,"column_start":12,"column_end":27},"name":"DefaultExecutor","qualname":"::global::DefaultExecutor","value":"DefaultExecutor {  }","parent":null,"children":[{"krate":0,"index":199}],"decl_id":null,"docs":" Executes futures on the default executor for the current execution context.","sig":null,"attributes":[]},{"kind":"Method","id":{"krate":0,"index":93},"span":{"file_name":"C:\\Users\\Administrator\\.cargo\\registry\\src\\github.com-1ecc6299db9ec823\\tokio-executor-0.1.8\\src\\global.rs","byte_start":15268,"byte_end":15275,"line_start":35,"line_end":35,"column_start":12,"column_end":19},"name":"current","qualname":"<DefaultExecutor>::current","value":"fn () -> DefaultExecutor","parent":null,"children":[],"decl_id":null,"docs":" Returns a handle to the default executor for the current context.","sig":null,"attributes":[]},{"kind":"Function","id":{"krate":0,"index":113},"span":{"file_name":"C:\\Users\\Administrator\\.cargo\\registry\\src\\github.com-1ecc6299db9ec823\\tokio-executor-0.1.8\\src\\global.rs","byte_start":19215,"byte_end":19220,"line_start":161,"line_end":161,"column_start":8,"column_end":13},"name":"spawn","qualname":"::global::spawn","value":"fn <T> (future: T) -> ()","parent":null,"children":[],"decl_id":null,"docs":" Submits a future for execution on the default executor -- usually a\n threadpool.","sig":null,"attributes":[]},{"kind":"Function","id":{"krate":0,"index":115},"span":{"file_name":"C:\\Users\\Administrator\\.cargo\\registry\\src\\github.com-1ecc6299db9ec823\\tokio-executor-0.1.8\\src\\global.rs","byte_start":19523,"byte_end":19535,"line_start":173,"line_end":173,"column_start":8,"column_end":20},"name":"with_default","qualname":"::global::with_default","value":"fn <T, F, R> (executor: &mut T, enter: &mut Enter, f: F) -> R","parent":null,"children":[],"decl_id":null,"docs":" Set the default executor for the duration of the closure","sig":null,"attributes":[]},{"kind":"Mod","id":{"krate":0,"index":130},"span":{"file_name":"C:\\Users\\Administrator\\.cargo\\registry\\src\\github.com-1ecc6299db9ec823\\tokio-executor-0.1.8\\src\\park.rs","byte_start":0,"byte_end":0,"line_start":1,"line_end":1,"column_start":1,"column_end":1},"name":"park","qualname":"::park","value":"C:\\Users\\Administrator\\.cargo\\registry\\src\\github.com-1ecc6299db9ec823\\tokio-executor-0.1.8\\src\\park.rs","parent":null,"children":[{"krate":0,"index":131},{"krate":0,"index":132},{"krate":0,"index":133},{"krate":0,"index":134},{"krate":0,"index":135},{"krate":0,"index":138},{"krate":0,"index":144},{"krate":0,"index":146},{"krate":0,"index":148},{"krate":0,"index":219},{"krate":0,"index":221},{"krate":0,"index":223},{"krate":0,"index":225},{"krate":0,"index":227},{"krate":0,"index":231},{"krate":0,"index":229},{"krate":0,"index":233},{"krate":0,"index":150},{"krate":0,"index":156},{"krate":0,"index":165}],"decl_id":null,"docs":" Abstraction over blocking and unblocking the current thread.","sig":null,"attributes":[]},{"kind":"Trait","id":{"krate":0,"index":138},"span":{"file_name":"C:\\Users\\Administrator\\.cargo\\registry\\src\\github.com-1ecc6299db9ec823\\tokio-executor-0.1.8\\src\\park.rs","byte_start":23788,"byte_end":23792,"line_start":59,"line_end":59,"column_start":11,"column_end":15},"name":"Park","qualname":"::park::Park","value":"Park","parent":null,"children":[{"krate":0,"index":139},{"krate":0,"index":140},{"krate":0,"index":141},{"krate":0,"index":142},{"krate":0,"index":143}],"decl_id":null,"docs":" Block the current thread.","sig":null,"attributes":[]},{"kind":"Type","id":{"krate":0,"index":139},"span":{"file_name":"C:\\Users\\Administrator\\.cargo\\registry\\src\\github.com-1ecc6299db9ec823\\tokio-executor-0.1.8\\src\\park.rs","byte_start":23862,"byte_end":23868,"line_start":61,"line_end":61,"column_start":10,"column_end":16},"name":"Unpark","qualname":"::park::Park::Unpark","value":"type Unpark: Unpark;","parent":{"krate":0,"index":138},"children":[],"decl_id":null,"docs":" Unpark handle type for the `Park` implementation.\n","sig":null,"attributes":[]},{"kind":"Type","id":{"krate":0,"index":140},"span":{"file_name":"C:\\Users\\Administrator\\.cargo\\registry\\src\\github.com-1ecc6299db9ec823\\tokio-executor-0.1.8\\src\\park.rs","byte_start":23921,"byte_end":23926,"line_start":64,"line_end":64,"column_start":10,"column_end":15},"name":"Error","qualname":"::park::Park::Error","value":"type Error;","parent":{"krate":0,"index":138},"children":[],"decl_id":null,"docs":" Error returned by `park`\n","sig":null,"attributes":[]},{"kind":"Method","id":{"krate":0,"index":141},"span":{"file_name":"C:\\Users\\Administrator\\.cargo\\registry\\src\\github.com-1ecc6299db9ec823\\tokio-executor-0.1.8\\src\\park.rs","byte_start":24008,"byte_end":24014,"line_start":67,"line_end":67,"column_start":8,"column_end":14},"name":"unpark","qualname":"::park::Park::unpark","value":"fn (&self) -> Self::Unpark","parent":{"krate":0,"index":138},"children":[],"decl_id":null,"docs":" Get a new `Unpark` handle associated with this `Park` instance.\n","sig":null,"attributes":[]},{"kind":"Method","id":{"krate":0,"index":142},"span":{"file_name":"C:\\Users\\Administrator\\.cargo\\registry\\src\\github.com-1ecc6299db9ec823\\tokio-executor-0.1.8\\src\\park.rs","byte_start":24661,"byte_end":24665,"line_start":84,"line_end":84,"column_start":8,"column_end":12},"name":"park","qualname":"::park::Park::park","value":"fn (&mut self) -> Result<(), Self::Error>","parent":{"krate":0,"index":138},"children":[],"decl_id":null,"docs":" Block the current thread unless or until the token is available.","sig":null,"attributes":[]},{"kind":"Method","id":{"krate":0,"index":143},"span":{"file_name":"C:\\Users\\Administrator\\.cargo\\registry\\src\\github.com-1ecc6299db9ec823\\tokio-executor-0.1.8\\src\\park.rs","byte_start":25391,"byte_end":25403,"line_start":104,"line_end":104,"column_start":8,"column_end":20},"name":"park_timeout","qualname":"::park::Park::park_timeout","value":"fn (&mut self, duration: Duration) -> Result<(), Self::Error>","parent":{"krate":0,"index":138},"children":[],"decl_id":null,"docs":" Park the current thread for at most `duration`.","sig":null,"attributes":[]},{"kind":"Trait","id":{"krate":0,"index":144},"span":{"file_name":"C:\\Users\\Administrator\\.cargo\\registry\\src\\github.com-1ecc6299db9ec823\\tokio-executor-0.1.8\\src\\park.rs","byte_start":25659,"byte_end":25665,"line_start":113,"line_end":113,"column_start":11,"column_end":17},"name":"Unpark","qualname":"::park::Unpark","value":"Unpark: Sync + Send + 'static","parent":null,"children":[{"krate":0,"index":145}],"decl_id":null,"docs":" Unblock a thread blocked by the associated [`Park`] instance.","sig":null,"attributes":[]},{"kind":"Method","id":{"krate":0,"index":145},"span":{"file_name":"C:\\Users\\Administrator\\.cargo\\registry\\src\\github.com-1ecc6299db9ec823\\tokio-executor-0.1.8\\src\\park.rs","byte_start":26215,"byte_end":26221,"line_start":128,"line_end":128,"column_start":8,"column_end":14},"name":"unpark","qualname":"::park::Unpark::unpark","value":"fn (&self) -> ()","parent":{"krate":0,"index":144},"children":[],"decl_id":null,"docs":" Unblock a thread that is blocked by the associated `Park` handle.","sig":null,"attributes":[]},{"kind":"Struct","id":{"krate":0,"index":219},"span":{"file_name":"C:\\Users\\Administrator\\.cargo\\registry\\src\\github.com-1ecc6299db9ec823\\tokio-executor-0.1.8\\src\\park.rs","byte_start":26950,"byte_end":26960,"line_start":154,"line_end":154,"column_start":12,"column_end":22},"name":"ParkThread","qualname":"::park::ParkThread","value":"ParkThread {  }","parent":null,"children":[{"krate":0,"index":220}],"decl_id":null,"docs":" Blocks the current thread using a condition variable.","sig":null,"attributes":[]},{"kind":"Struct","id":{"krate":0,"index":223},"span":{"file_name":"C:\\Users\\Administrator\\.cargo\\registry\\src\\github.com-1ecc6299db9ec823\\tokio-executor-0.1.8\\src\\park.rs","byte_start":27193,"byte_end":27202,"line_start":164,"line_end":164,"column_start":12,"column_end":21},"name":"ParkError","qualname":"::park::ParkError","value":"ParkError {  }","parent":null,"children":[{"krate":0,"index":224}],"decl_id":null,"docs":" Error returned by [`ParkThread`]","sig":null,"attributes":[]},{"kind":"Struct","id":{"krate":0,"index":227},"span":{"file_name":"C:\\Users\\Administrator\\.cargo\\registry\\src\\github.com-1ecc6299db9ec823\\tokio-executor-0.1.8\\src\\park.rs","byte_start":27311,"byte_end":27323,"line_start":170,"line_end":170,"column_start":12,"column_end":24},"name":"UnparkThread","qualname":"::park::UnparkThread","value":"UnparkThread {  }","parent":null,"children":[{"krate":0,"index":228}],"decl_id":null,"docs":" Unblocks a thread that was blocked by `ParkThread`.\n","sig":null,"attributes":[]},{"kind":"Method","id":{"krate":0,"index":151},"span":{"file_name":"C:\\Users\\Administrator\\.cargo\\registry\\src\\github.com-1ecc6299db9ec823\\tokio-executor-0.1.8\\src\\park.rs","byte_start":27685,"byte_end":27688,"line_start":185,"line_end":185,"column_start":12,"column_end":15},"name":"new","qualname":"<ParkThread>::new","value":"fn () -> ParkThread","parent":null,"children":[],"decl_id":null,"docs":" Create a new `ParkThread` handle for the current thread.","sig":null,"attributes":[]},{"kind":"Trait","id":{"krate":0,"index":169},"span":{"file_name":"C:\\Users\\Administrator\\.cargo\\registry\\src\\github.com-1ecc6299db9ec823\\tokio-executor-0.1.8\\src\\typed.rs","byte_start":30885,"byte_end":30898,"line_start":77,"line_end":77,"column_start":11,"column_end":24},"name":"TypedExecutor","qualname":"::typed::TypedExecutor","value":"TypedExecutor<T>","parent":null,"children":[{"krate":0,"index":171},{"krate":0,"index":172}],"decl_id":null,"docs":" A value that spawns futures of a specific type.","sig":null,"attributes":[]},{"kind":"Method","id":{"krate":0,"index":171},"span":{"file_name":"C:\\Users\\Administrator\\.cargo\\registry\\src\\github.com-1ecc6299db9ec823\\tokio-executor-0.1.8\\src\\typed.rs","byte_start":32109,"byte_end":32114,"line_start":117,"line_end":117,"column_start":8,"column_end":13},"name":"spawn","qualname":"::typed::TypedExecutor::spawn","value":"fn (&mut self, future: T) -> Result<(), SpawnError>","parent":{"krate":0,"index":169},"children":[],"decl_id":null,"docs":" Spawns a future to run on this executor.","sig":null,"attributes":[]},{"kind":"Method","id":{"krate":0,"index":172},"span":{"file_name":"C:\\Users\\Administrator\\.cargo\\registry\\src\\github.com-1ecc6299db9ec823\\tokio-executor-0.1.8\\src\\typed.rs","byte_start":33650,"byte_end":33656,"line_start":165,"line_end":165,"column_start":8,"column_end":14},"name":"status","qualname":"::typed::TypedExecutor::status","value":"fn (&self) -> Result<(), SpawnError>","parent":{"krate":0,"index":169},"children":[],"decl_id":null,"docs":" Provides a best effort **hint** to whether or not `spawn` will succeed.","sig":null,"attributes":[]}],"impls":[{"id":0,"kind":"Direct","span":{"file_name":"C:\\Users\\Administrator\\.cargo\\registry\\src\\github.com-1ecc6299db9ec823\\tokio-executor-0.1.8\\src\\enter.rs","byte_start":3369,"byte_end":3379,"line_start":24,"line_end":24,"column_start":21,"column_end":31},"value":"","parent":null,"children":[{"krate":0,"index":28}],"docs":"","sig":null,"attributes":[]},{"id":1,"kind":"Direct","span":{"file_name":"C:\\Users\\Administrator\\.cargo\\registry\\src\\github.com-1ecc6299db9ec823\\tokio-executor-0.1.8\\src\\enter.rs","byte_start":3581,"byte_end":3591,"line_start":32,"line_end":32,"column_start":23,"column_end":33},"value":"","parent":null,"children":[{"krate":0,"index":30}],"docs":"","sig":null,"attributes":[]},{"id":2,"kind":"Direct","span":{"file_name":"C:\\Users\\Administrator\\.cargo\\registry\\src\\github.com-1ecc6299db9ec823\\tokio-executor-0.1.8\\src\\enter.rs","byte_start":3725,"byte_end":3735,"line_start":38,"line_end":38,"column_start":16,"column_end":26},"value":"","parent":null,"children":[{"krate":0,"index":32}],"docs":"","sig":null,"attributes":[]},{"id":3,"kind":"Direct","span":{"file_name":"C:\\Users\\Administrator\\.cargo\\registry\\src\\github.com-1ecc6299db9ec823\\tokio-executor-0.1.8\\src\\enter.rs","byte_start":5014,"byte_end":5019,"line_start":81,"line_end":81,"column_start":19,"column_end":24},"value":"","parent":null,"children":[{"krate":0,"index":41}],"docs":"","sig":null,"attributes":[]},{"id":4,"kind":"Inherent","span":{"file_name":"C:\\Users\\Administrator\\.cargo\\registry\\src\\github.com-1ecc6299db9ec823\\tokio-executor-0.1.8\\src\\enter.rs","byte_start":5438,"byte_end":5443,"line_start":106,"line_end":106,"column_start":6,"column_end":11},"value":"","parent":null,"children":[{"krate":0,"index":46},{"krate":0,"index":48},{"krate":0,"index":49}],"docs":"","sig":null,"attributes":[]},{"id":5,"kind":"Direct","span":{"file_name":"C:\\Users\\Administrator\\.cargo\\registry\\src\\github.com-1ecc6299db9ec823\\tokio-executor-0.1.8\\src\\enter.rs","byte_start":6257,"byte_end":6262,"line_start":132,"line_end":132,"column_start":21,"column_end":26},"value":"","parent":null,"children":[{"krate":0,"index":52}],"docs":"","sig":null,"attributes":[]},{"id":6,"kind":"Direct","span":{"file_name":"C:\\Users\\Administrator\\.cargo\\registry\\src\\github.com-1ecc6299db9ec823\\tokio-executor-0.1.8\\src\\enter.rs","byte_start":6388,"byte_end":6393,"line_start":138,"line_end":138,"column_start":15,"column_end":20},"value":"","parent":null,"children":[{"krate":0,"index":54}],"docs":"","sig":null,"attributes":[]},{"id":7,"kind":"Direct","span":{"file_name":"C:\\Users\\Administrator\\.cargo\\registry\\src\\github.com-1ecc6299db9ec823\\tokio-executor-0.1.8\\src\\enter.rs","byte_start":6798,"byte_end":6799,"line_start":160,"line_end":160,"column_start":42,"column_end":43},"value":"","parent":null,"children":[{"krate":0,"index":60}],"docs":"","sig":null,"attributes":[]},{"id":8,"kind":"Inherent","span":{"file_name":"C:\\Users\\Administrator\\.cargo\\registry\\src\\github.com-1ecc6299db9ec823\\tokio-executor-0.1.8\\src\\error.rs","byte_start":7428,"byte_end":7438,"line_start":18,"line_end":18,"column_start":6,"column_end":16},"value":"","parent":null,"children":[{"krate":0,"index":65},{"krate":0,"index":66},{"krate":0,"index":67},{"krate":0,"index":68}],"docs":"","sig":null,"attributes":[]},{"id":9,"kind":"Direct","span":{"file_name":"C:\\Users\\Administrator\\.cargo\\registry\\src\\github.com-1ecc6299db9ec823\\tokio-executor-0.1.8\\src\\error.rs","byte_start":8081,"byte_end":8091,"line_start":40,"line_end":40,"column_start":23,"column_end":33},"value":"","parent":null,"children":[{"krate":0,"index":70}],"docs":"","sig":null,"attributes":[]},{"id":10,"kind":"Direct","span":{"file_name":"C:\\Users\\Administrator\\.cargo\\registry\\src\\github.com-1ecc6299db9ec823\\tokio-executor-0.1.8\\src\\error.rs","byte_start":8225,"byte_end":8235,"line_start":46,"line_end":46,"column_start":16,"column_end":26},"value":"","parent":null,"children":[{"krate":0,"index":72}],"docs":"","sig":null,"attributes":[]},{"id":11,"kind":"Direct","span":{"file_name":"C:\\Users\\Administrator\\.cargo\\registry\\src\\github.com-1ecc6299db9ec823\\tokio-executor-0.1.8\\src\\executor.rs","byte_start":13594,"byte_end":13597,"line_start":140,"line_end":140,"column_start":41,"column_end":44},"value":"","parent":null,"children":[{"krate":0,"index":81},{"krate":0,"index":82}],"docs":"","sig":null,"attributes":[]},{"id":12,"kind":"Inherent","span":{"file_name":"C:\\Users\\Administrator\\.cargo\\registry\\src\\github.com-1ecc6299db9ec823\\tokio-executor-0.1.8\\src\\global.rs","byte_start":14520,"byte_end":14535,"line_start":22,"line_end":22,"column_start":6,"column_end":21},"value":"","parent":null,"children":[{"krate":0,"index":93},{"krate":0,"index":94}],"docs":"","sig":null,"attributes":[]},{"id":13,"kind":"Direct","span":{"file_name":"C:\\Users\\Administrator\\.cargo\\registry\\src\\github.com-1ecc6299db9ec823\\tokio-executor-0.1.8\\src\\global.rs","byte_start":16353,"byte_end":16368,"line_start":72,"line_end":72,"column_start":26,"column_end":41},"value":"","parent":null,"children":[{"krate":0,"index":99},{"krate":0,"index":102}],"docs":"","sig":null,"attributes":[]},{"id":14,"kind":"Direct","span":{"file_name":"C:\\Users\\Administrator\\.cargo\\registry\\src\\github.com-1ecc6299db9ec823\\tokio-executor-0.1.8\\src\\global.rs","byte_start":16859,"byte_end":16874,"line_start":87,"line_end":87,"column_start":37,"column_end":52},"value":"","parent":null,"children":[{"krate":0,"index":107},{"krate":0,"index":108}],"docs":"","sig":null,"attributes":[]},{"id":15,"kind":"Direct","span":{"file_name":"C:\\Users\\Administrator\\.cargo\\registry\\src\\github.com-1ecc6299db9ec823\\tokio-executor-0.1.8\\src\\global.rs","byte_start":17191,"byte_end":17206,"line_start":100,"line_end":100,"column_start":33,"column_end":48},"value":"","parent":null,"children":[{"krate":0,"index":111}],"docs":"","sig":null,"attributes":[]},{"id":16,"kind":"Direct","span":{"file_name":"C:\\Users\\Administrator\\.cargo\\registry\\src\\github.com-1ecc6299db9ec823\\tokio-executor-0.1.8\\src\\global.rs","byte_start":20100,"byte_end":20105,"line_start":190,"line_end":190,"column_start":27,"column_end":32},"value":"","parent":null,"children":[{"krate":0,"index":126}],"docs":"","sig":null,"attributes":[]},{"id":17,"kind":"Direct","span":{"file_name":"C:\\Users\\Administrator\\.cargo\\registry\\src\\github.com-1ecc6299db9ec823\\tokio-executor-0.1.8\\src\\park.rs","byte_start":26249,"byte_end":26252,"line_start":131,"line_end":131,"column_start":17,"column_end":20},"value":"","parent":null,"children":[{"krate":0,"index":147}],"docs":"","sig":null,"attributes":[]},{"id":18,"kind":"Direct","span":{"file_name":"C:\\Users\\Administrator\\.cargo\\registry\\src\\github.com-1ecc6299db9ec823\\tokio-executor-0.1.8\\src\\park.rs","byte_start":26337,"byte_end":26340,"line_start":137,"line_end":137,"column_start":17,"column_end":20},"value":"","parent":null,"children":[{"krate":0,"index":149}],"docs":"","sig":null,"attributes":[]},{"id":19,"kind":"Inherent","span":{"file_name":"C:\\Users\\Administrator\\.cargo\\registry\\src\\github.com-1ecc6299db9ec823\\tokio-executor-0.1.8\\src\\park.rs","byte_start":27457,"byte_end":27467,"line_start":180,"line_end":180,"column_start":6,"column_end":16},"value":"","parent":null,"children":[{"krate":0,"index":151},{"krate":0,"index":152}],"docs":"","sig":null,"attributes":[]},{"id":20,"kind":"Direct","span":{"file_name":"C:\\Users\\Administrator\\.cargo\\registry\\src\\github.com-1ecc6299db9ec823\\tokio-executor-0.1.8\\src\\park.rs","byte_start":28009,"byte_end":28019,"line_start":200,"line_end":200,"column_start":15,"column_end":25},"value":"","parent":null,"children":[{"krate":0,"index":157},{"krate":0,"index":158},{"krate":0,"index":159},{"krate":0,"index":161},{"krate":0,"index":163}],"docs":"","sig":null,"attributes":[]},{"id":21,"kind":"Direct","span":{"file_name":"C:\\Users\\Administrator\\.cargo\\registry\\src\\github.com-1ecc6299db9ec823\\tokio-executor-0.1.8\\src\\park.rs","byte_start":28575,"byte_end":28587,"line_start":222,"line_end":222,"column_start":17,"column_end":29},"value":"","parent":null,"children":[{"krate":0,"index":166}],"docs":"","sig":null,"attributes":[]},{"id":22,"kind":"Direct","span":{"file_name":"C:\\Users\\Administrator\\.cargo\\registry\\src\\github.com-1ecc6299db9ec823\\tokio-executor-0.1.8\\src\\typed.rs","byte_start":33748,"byte_end":33751,"line_start":170,"line_end":170,"column_start":33,"column_end":36},"value":"","parent":null,"children":[{"krate":0,"index":176},{"krate":0,"index":177}],"docs":"","sig":null,"attributes":[]}],"refs":[{"kind":"Mod","span":{"file_name":"C:\\Users\\Administrator\\.cargo\\registry\\src\\github.com-1ecc6299db9ec823\\tokio-executor-0.1.8\\src\\lib.rs","byte_start":2658,"byte_end":2662,"line_start":63,"line_end":63,"column_start":9,"column_end":13},"ref_id":{"krate":0,"index":130}}],"macro_refs":[],"relations":[{"span":{"file_name":"C:\\Users\\Administrator\\.cargo\\registry\\src\\github.com-1ecc6299db9ec823\\tokio-executor-0.1.8\\src\\enter.rs","byte_start":3369,"byte_end":3379,"line_start":24,"line_end":24,"column_start":21,"column_end":31},"kind":{"Impl":{"id":0}},"from":{"krate":0,"index":25},"to":{"krate":2,"index":7486}},{"span":{"file_name":"C:\\Users\\Administrator\\.cargo\\registry\\src\\github.com-1ecc6299db9ec823\\tokio-executor-0.1.8\\src\\enter.rs","byte_start":3581,"byte_end":3591,"line_start":32,"line_end":32,"column_start":23,"column_end":33},"kind":{"Impl":{"id":1}},"from":{"krate":0,"index":25},"to":{"krate":2,"index":7491}},{"span":{"file_name":"C:\\Users\\Administrator\\.cargo\\registry\\src\\github.com-1ecc6299db9ec823\\tokio-executor-0.1.8\\src\\enter.rs","byte_start":3725,"byte_end":3735,"line_start":38,"line_end":38,"column_start":16,"column_end":26},"kind":{"Impl":{"id":2}},"from":{"krate":0,"index":25},"to":{"krate":1,"index":1599}},{"span":{"file_name":"C:\\Users\\Administrator\\.cargo\\registry\\src\\github.com-1ecc6299db9ec823\\tokio-executor-0.1.8\\src\\enter.rs","byte_start":5014,"byte_end":5019,"line_start":81,"line_end":81,"column_start":19,"column_end":24},"kind":{"Impl":{"id":3}},"from":{"krate":0,"index":38},"to":{"krate":2,"index":1725}},{"span":{"file_name":"C:\\Users\\Administrator\\.cargo\\registry\\src\\github.com-1ecc6299db9ec823\\tokio-executor-0.1.8\\src\\enter.rs","byte_start":5438,"byte_end":5443,"line_start":106,"line_end":106,"column_start":6,"column_end":11},"kind":{"Impl":{"id":4}},"from":{"krate":0,"index":22},"to":{"krate":4294967295,"index":4294967295}},{"span":{"file_name":"C:\\Users\\Administrator\\.cargo\\registry\\src\\github.com-1ecc6299db9ec823\\tokio-executor-0.1.8\\src\\enter.rs","byte_start":6257,"byte_end":6262,"line_start":132,"line_end":132,"column_start":21,"column_end":26},"kind":{"Impl":{"id":5}},"from":{"krate":0,"index":22},"to":{"krate":2,"index":7486}},{"span":{"file_name":"C:\\Users\\Administrator\\.cargo\\registry\\src\\github.com-1ecc6299db9ec823\\tokio-executor-0.1.8\\src\\enter.rs","byte_start":6388,"byte_end":6393,"line_start":138,"line_end":138,"column_start":15,"column_end":20},"kind":{"Impl":{"id":6}},"from":{"krate":0,"index":22},"to":{"krate":2,"index":1725}},{"span":{"file_name":"C:\\Users\\Administrator\\.cargo\\registry\\src\\github.com-1ecc6299db9ec823\\tokio-executor-0.1.8\\src\\enter.rs","byte_start":6798,"byte_end":6799,"line_start":160,"line_end":160,"column_start":42,"column_end":43},"kind":{"Impl":{"id":7}},"from":{"krate":0,"index":59},"to":{"krate":0,"index":56}},{"span":{"file_name":"C:\\Users\\Administrator\\.cargo\\registry\\src\\github.com-1ecc6299db9ec823\\tokio-executor-0.1.8\\src\\error.rs","byte_start":7428,"byte_end":7438,"line_start":18,"line_end":18,"column_start":6,"column_end":16},"kind":{"Impl":{"id":8}},"from":{"krate":0,"index":194},"to":{"krate":4294967295,"index":4294967295}},{"span":{"file_name":"C:\\Users\\Administrator\\.cargo\\registry\\src\\github.com-1ecc6299db9ec823\\tokio-executor-0.1.8\\src\\error.rs","byte_start":8081,"byte_end":8091,"line_start":40,"line_end":40,"column_start":23,"column_end":33},"kind":{"Impl":{"id":9}},"from":{"krate":0,"index":194},"to":{"krate":2,"index":7491}},{"span":{"file_name":"C:\\Users\\Administrator\\.cargo\\registry\\src\\github.com-1ecc6299db9ec823\\tokio-executor-0.1.8\\src\\error.rs","byte_start":8225,"byte_end":8235,"line_start":46,"line_end":46,"column_start":16,"column_end":26},"kind":{"Impl":{"id":10}},"from":{"krate":0,"index":194},"to":{"krate":1,"index":1599}},{"span":{"file_name":"C:\\Users\\Administrator\\.cargo\\registry\\src\\github.com-1ecc6299db9ec823\\tokio-executor-0.1.8\\src\\executor.rs","byte_start":13594,"byte_end":13597,"line_start":140,"line_end":140,"column_start":41,"column_end":44},"kind":{"Impl":{"id":11}},"from":{"krate":5,"index":90},"to":{"krate":0,"index":76}},{"span":{"file_name":"C:\\Users\\Administrator\\.cargo\\registry\\src\\github.com-1ecc6299db9ec823\\tokio-executor-0.1.8\\src\\global.rs","byte_start":14520,"byte_end":14535,"line_start":22,"line_end":22,"column_start":6,"column_end":21},"kind":{"Impl":{"id":12}},"from":{"krate":0,"index":198},"to":{"krate":4294967295,"index":4294967295}},{"span":{"file_name":"C:\\Users\\Administrator\\.cargo\\registry\\src\\github.com-1ecc6299db9ec823\\tokio-executor-0.1.8\\src\\global.rs","byte_start":16353,"byte_end":16368,"line_start":72,"line_end":72,"column_start":26,"column_end":41},"kind":{"Impl":{"id":13}},"from":{"krate":0,"index":198},"to":{"krate":0,"index":76}},{"span":{"file_name":"C:\\Users\\Administrator\\.cargo\\registry\\src\\github.com-1ecc6299db9ec823\\tokio-executor-0.1.8\\src\\global.rs","byte_start":16859,"byte_end":16874,"line_start":87,"line_end":87,"column_start":37,"column_end":52},"kind":{"Impl":{"id":14}},"from":{"krate":0,"index":198},"to":{"krate":0,"index":169}},{"span":{"file_name":"C:\\Users\\Administrator\\.cargo\\registry\\src\\github.com-1ecc6299db9ec823\\tokio-executor-0.1.8\\src\\global.rs","byte_start":17191,"byte_end":17206,"line_start":100,"line_end":100,"column_start":33,"column_end":48},"kind":{"Impl":{"id":15}},"from":{"krate":0,"index":198},"to":{"krate":18,"index":559}},{"span":{"file_name":"C:\\Users\\Administrator\\.cargo\\registry\\src\\github.com-1ecc6299db9ec823\\tokio-executor-0.1.8\\src\\global.rs","byte_start":20100,"byte_end":20105,"line_start":190,"line_end":190,"column_start":27,"column_end":32},"kind":{"Impl":{"id":16}},"from":{"krate":0,"index":120},"to":{"krate":2,"index":1725}},{"span":{"file_name":"C:\\Users\\Administrator\\.cargo\\registry\\src\\github.com-1ecc6299db9ec823\\tokio-executor-0.1.8\\src\\park.rs","byte_start":25667,"byte_end":25671,"line_start":113,"line_end":113,"column_start":19,"column_end":23},"kind":"SuperTrait","from":{"krate":2,"index":1544},"to":{"krate":0,"index":144}},{"span":{"file_name":"C:\\Users\\Administrator\\.cargo\\registry\\src\\github.com-1ecc6299db9ec823\\tokio-executor-0.1.8\\src\\park.rs","byte_start":25674,"byte_end":25678,"line_start":113,"line_end":113,"column_start":26,"column_end":30},"kind":"SuperTrait","from":{"krate":2,"index":1534},"to":{"krate":0,"index":144}},{"span":{"file_name":"C:\\Users\\Administrator\\.cargo\\registry\\src\\github.com-1ecc6299db9ec823\\tokio-executor-0.1.8\\src\\park.rs","byte_start":26249,"byte_end":26252,"line_start":131,"line_end":131,"column_start":17,"column_end":20},"kind":{"Impl":{"id":17}},"from":{"krate":5,"index":90},"to":{"krate":0,"index":144}},{"span":{"file_name":"C:\\Users\\Administrator\\.cargo\\registry\\src\\github.com-1ecc6299db9ec823\\tokio-executor-0.1.8\\src\\park.rs","byte_start":26337,"byte_end":26340,"line_start":137,"line_end":137,"column_start":17,"column_end":20},"kind":{"Impl":{"id":18}},"from":{"krate":5,"index":2394},"to":{"krate":0,"index":144}},{"span":{"file_name":"C:\\Users\\Administrator\\.cargo\\registry\\src\\github.com-1ecc6299db9ec823\\tokio-executor-0.1.8\\src\\park.rs","byte_start":27457,"byte_end":27467,"line_start":180,"line_end":180,"column_start":6,"column_end":16},"kind":{"Impl":{"id":19}},"from":{"krate":0,"index":219},"to":{"krate":4294967295,"index":4294967295}},{"span":{"file_name":"C:\\Users\\Administrator\\.cargo\\registry\\src\\github.com-1ecc6299db9ec823\\tokio-executor-0.1.8\\src\\park.rs","byte_start":28009,"byte_end":28019,"line_start":200,"line_end":200,"column_start":15,"column_end":25},"kind":{"Impl":{"id":20}},"from":{"krate":0,"index":219},"to":{"krate":0,"index":138}},{"span":{"file_name":"C:\\Users\\Administrator\\.cargo\\registry\\src\\github.com-1ecc6299db9ec823\\tokio-executor-0.1.8\\src\\park.rs","byte_start":28575,"byte_end":28587,"line_start":222,"line_end":222,"column_start":17,"column_end":29},"kind":{"Impl":{"id":21}},"from":{"krate":0,"index":227},"to":{"krate":0,"index":144}},{"span":{"file_name":"C:\\Users\\Administrator\\.cargo\\registry\\src\\github.com-1ecc6299db9ec823\\tokio-executor-0.1.8\\src\\typed.rs","byte_start":33748,"byte_end":33751,"line_start":170,"line_end":170,"column_start":33,"column_end":36},"kind":{"Impl":{"id":22}},"from":{"krate":5,"index":90},"to":{"krate":0,"index":169}}]}